MANIFEST.in
README.md
requirements.txt
setup.cfg
setup.py
checkist/__init__.py
checkist/checkist.py
checkist.egg-info/PKG-INFO
checkist.egg-info/SOURCES.txt
checkist.egg-info/dependency_links.txt
checkist.egg-info/top_level.txt
test/test_main.py