Metadata-Version: 1.0
Name: checkist
Version: 1.0.0
Summary: minimal module for argument checking
Home-page: https://github.com/freeman-lab/checkist
Author: freeman-lab
Author-email: the.freeman.lab@gmail.com
License: UNKNOWN
Platform: UNKNOWN
